DDetector/__init__.py
DDetector/detector.py
DDetector-0.0.3.dist-info/METADATA
DDetector-0.0.3.dist-info/WHEEL
DDetector-0.0.3.dist-info/top_level.txt
DDetector-0.0.3.dist-info/RECORD
