Metadata-Version: 2.1
Name: DDetector
Version: 0.0.3
Summary: Data distribution detector
Home-page: https://github.com/JonnesLin/distribution_detection
Author: Jones Lin
Author-email: jonneslin@gmail.com
License: UNKNOWN
Platform: UNKNOWN
Classifier: Programming Language :: Python :: 3
Classifier: License :: OSI Approved :: MIT License
Classifier: Operating System :: OS Independent
Requires-Dist: scikit-learn
